flatwhite/__init__.py
flatwhite/benchmark.py
flatwhite/file_handler.py
flatwhite/format_validator.py
flatwhite/templates.py
flatwhite/web_scraper.py
tests/__init__.py
tests/test_file_handler.py
tests/test_format_validator.py
flatwhite-0.4.0.dist-info/LICENSE
flatwhite-0.4.0.dist-info/METADATA
flatwhite-0.4.0.dist-info/WHEEL
flatwhite-0.4.0.dist-info/top_level.txt
flatwhite-0.4.0.dist-info/RECORD
