Metadata-Version: 2.1
Name: flatwhite
Version: 0.4.0
Summary: A package for validating formats and handling files.
Home-page: https://github.com/Ferref/flatwhite
Author: Ferenc Kovács
Author-email: kovacsferenc026@gmail.com
License: MIT
License-File: LICENSE
Requires-Dist: requests
Requires-Dist: re
Requires-Dist: smtplib
Requires-Dist: datetime
Requires-Dist: os
Requires-Dist: shutil
